riskCalculator/__init__.py
riskCalculator/expectedSurvivors.py
riskCalculator/likelihoodOfVictory.py
riskCalculator/main.py
riskCalculator/parseArguments.py
riskCalculator/probabilityOfLosses.py
riskCalculator/readWriteData.py
riskCalculator/recursiveMarkovChain.py
riskCalculator/risk.py
riskCalculator-0.0.5.dist-info/LICENSE
riskCalculator-0.0.5.dist-info/METADATA
riskCalculator-0.0.5.dist-info/WHEEL
riskCalculator-0.0.5.dist-info/top_level.txt
riskCalculator-0.0.5.dist-info/RECORD
