Metadata-Version: 2.1
Name: riskCalculator
Version: 0.0.5
Summary: Simple python package for calculating expected outcome of a risk battle
Author: Angus Leck
Author-email: aleck42@gmail.com
Keywords: python,first package
Classifier: Development Status :: 3 - Alpha
Classifier: Intended Audience :: Education
Classifier: Programming Language :: Python :: 2
Classifier: Programming Language :: Python :: 3
Classifier: Operating System :: MacOS :: MacOS X
Classifier: Operating System :: Microsoft :: Windows
License-File: LICENSE
